ncempy/README.rst
ncempy/__init__.py
ncempy/examples.rst
ncempy/long_description.rst
ncempy/algo/__init__.py
ncempy/algo/distortion.py
ncempy/algo/fourier_operations.py
ncempy/algo/gaussND.py
ncempy/algo/local_max.py
ncempy/algo/math.py
ncempy/algo/multicorr_funcs.py
ncempy/algo/peak_find.py
ncempy/algo/radial_profile.py
ncempy/command_line/__init__.py
ncempy/command_line/ncem2png.py
ncempy/edstomo/CharacteristicEmission.py
ncempy/edstomo/DoGenfire.py
ncempy/edstomo/__init__.py
ncempy/edstomo/bruker.py
ncempy/edstomo/postprocess.py
ncempy/edstomo/preprocess.py
ncempy/edstomo/Elam/ElamDB12.txt
ncempy/eval/__init__.py
ncempy/eval/line_profile.py
ncempy/eval/multicorr.py
ncempy/eval/ring_diff.py
ncempy/eval/stack_align.py
ncempy/io/__init__.py
ncempy/io/dectris.py
ncempy/io/dm.py
ncempy/io/emd.py
ncempy/io/emdVelox.py
ncempy/io/mrc.py
ncempy/io/ser.py
ncempy/io/smv.py
ncempy/viz/__init__.py
ncempy-1.15.dist-info/licenses/LICENSE
ncempy-1.15.dist-info/METADATA
ncempy-1.15.dist-info/WHEEL
ncempy-1.15.dist-info/entry_points.txt
ncempy-1.15.dist-info/top_level.txt
ncempy-1.15.dist-info/RECORD
